quickeepass
