Metadata-Version: 1.1
Name: QuicKeepass
Version: 0.6
Summary: Efficiently autotype your password from keepass on i3 using rofi 
Home-page: https://github.com/nongiach/QuicKeepass
Author: @chaignc
Author-email: UNKNOWN
License: UNKNOWN
Keywords: keepass,rofi,password,quick,manager,autotype,autofill
Platform: UNKNOWN
Classifier: License :: OSI Approved :: MIT License
Classifier: Programming Language :: Python :: 3
